[
  {
    "name": "com.azure.security.keyvault.secrets.implementation.models.SecretBundle",
    "allDeclaredConstructors": true,
    "allPublicConstructors": true,
    "allDeclaredMethods": true,
    "allPublicMethods": true,
    "allDeclaredFields": true,
    "allPublicFields": true,
    "methods": [
      { "name": "<init>", "parameterTypes": [] },
      { "name": "<init>", "parameterTypes": ["java.lang.String"] }
    ]
  },
  {
    "name": "com.azure.security.keyvault.secrets.implementation.models.SecretItem",
    "allDeclaredConstructors": true,
    "allPublicConstructors": true,
    "allDeclaredMethods": true,
    "allPublicMethods": true,
    "allDeclaredFields": true,
    "allPublicFields": true,
    "methods": [
      { "name": "<init>", "parameterTypes": [] }
    ]
  },
  {
    "name": "com.azure.security.keyvault.secrets.implementation.models.SecretAttributes",
    "allDeclaredConstructors": true,
    "allPublicConstructors": true,
    "allDeclaredMethods": true,
    "allPublicMethods": true,
    "allDeclaredFields": true,
    "allPublicFields": true,
    "methods": [
      { "name": "<init>", "parameterTypes": [] }
    ]
  },
  {
    "name": "com.azure.security.keyvault.secrets.implementation.models.SecretProperties",
    "allDeclaredConstructors": true,
    "allPublicConstructors": true,
    "allDeclaredMethods": true,
    "allPublicMethods": true,
    "allDeclaredFields": true,
    "allPublicFields": true,
    "methods": [
      { "name": "<init>", "parameterTypes": [] }
    ]
  },
  {
    "name": "com.azure.security.keyvault.secrets.models.KeyVaultSecret",
    "allDeclaredConstructors": true,
    "allPublicConstructors": true,
    "allDeclaredMethods": true,
    "allPublicMethods": true,
    "allDeclaredFields": true,
    "allPublicFields": true,
    "methods": [
      { "name": "<init>", "parameterTypes": [] },
      { "name": "<init>", "parameterTypes": ["java.lang.String", "java.lang.String"] }
    ]
  },
  {
    "name": "com.azure.identity.implementation.RegionalAuthority",
    "allDeclaredConstructors": true,
    "allPublicConstructors": true,
    "allDeclaredMethods": true,
    "allPublicMethods": true,
    "allDeclaredFields": true,
    "allPublicFields": true,
    "methods": [
      { "name": "<init>", "parameterTypes": [] },
      { "name": "<init>", "parameterTypes": ["java.lang.String"] }
    ]
  },
  {
    "name": "com.azure.security.keyvault.secrets.implementation.models.DeletionRecoveryLevel",
    "allDeclaredConstructors": true,
    "allPublicConstructors": true,
    "allDeclaredMethods": true,
    "allPublicMethods": true,
    "allDeclaredFields": true,
    "allPublicFields": true,
    "methods": [
      { "name": "<init>", "parameterTypes": [] }
    ]
  },
  {
    "name": "com.azure.core.util.ExpandableStringEnum",
    "allDeclaredConstructors": true,
    "allPublicConstructors": true,
    "allDeclaredMethods": true,
    "allPublicMethods": true,
    "allDeclaredFields": true,
    "allPublicFields": true,
    "methods": [
      { "name": "<init>", "parameterTypes": [] }
    ]
  },
  {
    "name": "com.fasterxml.jackson.databind.ObjectMapper",
    "allDeclaredConstructors": true,
    "allPublicConstructors": true,
    "allDeclaredMethods": true,
    "allPublicMethods": true,
    "allDeclaredFields": true,
    "allPublicFields": true
  },
  {
    "name": "com.fasterxml.jackson.annotation.JsonCreator",
    "allDeclaredConstructors": true,
    "allPublicConstructors": true,
    "allDeclaredMethods": true,
    "allPublicMethods": true,
    "allDeclaredFields": true,
    "allPublicFields": true
  },
  {
    "name": "com.fasterxml.jackson.annotation.JsonProperty",
    "allDeclaredConstructors": true,
    "allPublicConstructors": true,
    "allDeclaredMethods": true,
    "allPublicMethods": true,
    "allDeclaredFields": true,
    "allPublicFields": true
  }
] 